korea_weather_mcp/__init__.py
korea_weather_mcp/weather.py
korea_weather_mcp-0.1.0.dist-info/METADATA
korea_weather_mcp-0.1.0.dist-info/WHEEL
korea_weather_mcp-0.1.0.dist-info/entry_points.txt
korea_weather_mcp-0.1.0.dist-info/licenses/LICENSE
korea_weather_mcp-0.1.0.dist-info/RECORD
