Metadata-Version: 2.4
Name: korea-weather-mcp
Version: 0.1.0
Summary: MCP server for Korean weather forecasts using KMA API
Project-URL: Homepage, https://github.com/wowzoo/korea-weather-mcp
Project-URL: Repository, https://github.com/wowzoo/korea-weather-mcp
Project-URL: Issues, https://github.com/wowzoo/korea-weather-mcp/issues
Author-email: wowzoo <wowzoo@gmail.com>
License: MIT
License-File: LICENSE
Classifier: Development Status :: 3 - Alpha
Classifier: Intended Audience :: Developers
Classifier: License :: OSI Approved :: MIT License
Classifier: Programming Language :: Python :: 3
Classifier: Programming Language :: Python :: 3.13
Requires-Python: >=3.13
Requires-Dist: fastmcp>=2.3.4
